monokel/__init__.py
monokel/build.py
monokel/cli.py
monokel/run.py
monokel/templates/Dockerfile
monokel/templates/docker-compose.yml
monokel/templates/requirements.txt
monokel-0.0.6.dist-info/LICENSE.md
monokel-0.0.6.dist-info/METADATA
monokel-0.0.6.dist-info/WHEEL
monokel-0.0.6.dist-info/entry_points.txt
monokel-0.0.6.dist-info/top_level.txt
monokel-0.0.6.dist-info/RECORD
