Metadata-Version: 2.1
Name: monokel
Version: 0.0.6
Summary: A simple but flexible and containerized observer pipeline for filesystem events featured by docker.
Author: Rico Koschmitzky
Author-email: contact@ricokoschmitzky.com
Maintainer-email: Rico Koschmitzky <contact@ricokoschmitzky.com>
License: MIT License
Project-URL: repository, https://github.com/rkoschmitzky/monokel
Keywords: python,docker,events,pipeline,docker-compose,watchdog
Classifier: Development Status :: 3 - Alpha
Classifier: Programming Language :: Python
Classifier: Operating System :: OS Independent
Classifier: License :: OSI Approved :: MIT License
Requires-Python: >=3.6
License-File: LICENSE.md
Requires-Dist: pipreqs (==0.4.11)
Provides-Extra: watchdog
Requires-Dist: watchdog (==2.2.1) ; extra == 'watchdog'
